EzOpcuaServer/__init__.py
EzOpcuaServer-0.1.dist-info/LICENCE
EzOpcuaServer-0.1.dist-info/METADATA
EzOpcuaServer-0.1.dist-info/WHEEL
EzOpcuaServer-0.1.dist-info/top_level.txt
EzOpcuaServer-0.1.dist-info/RECORD
